pysolve3/__init__.py
pysolve3/equation.py
pysolve3/model.py
pysolve3/parameter.py
pysolve3/utils.py
pysolve3/variable.py
pysolve3/tests/__init__.py
pysolve3/tests/ch3_sim.py
pysolve3/tests/ch3_simex.py
pysolve3/tests/ch5_lp.py
pysolve3/tests/test_equation.py
pysolve3/tests/test_model.py
pysolve3/tests/test_parameter.py
pysolve3/tests/test_variable.py
pysolve3-0.1.5.dist-info/DESCRIPTION.rst
pysolve3-0.1.5.dist-info/METADATA
pysolve3-0.1.5.dist-info/RECORD
pysolve3-0.1.5.dist-info/WHEEL
pysolve3-0.1.5.dist-info/metadata.json
pysolve3-0.1.5.dist-info/top_level.txt
