Metadata-Version: 2.0
Name: pysolve3
Version: 0.1.5
Summary: A simple interface for solving systems of linear equations
Home-page: https://github.com/gpetrini/pysolve3
Author: Gabriel Petrini da Silveira
Author-email: gpetrinidasilveira@gmail.com
License: MIT
Platform: UNKNOWN
Requires-Dist: sympy (>=1.4)
Requires-Dist: numpy
Requires-Dist: pandas
